lavinhash-1.0.0.dist-info/METADATA
lavinhash-1.0.0.dist-info/WHEEL
lavinhash/__init__.py
lavinhash/lavinhash.cp313-win_amd64.pyd
lavinhash-1.0.0.dist-info/RECORD
