Metadata-Version: 2.4
Name: lavinhash
Version: 1.0.0
Classifier: Development Status :: 5 - Production/Stable
Classifier: Intended Audience :: Developers
Classifier: Intended Audience :: Science/Research
Classifier: License :: OSI Approved :: MIT License
Classifier: Operating System :: OS Independent
Classifier: Programming Language :: Python :: 3
Classifier: Programming Language :: Python :: 3.8
Classifier: Programming Language :: Python :: 3.9
Classifier: Programming Language :: Python :: 3.10
Classifier: Programming Language :: Python :: 3.11
Classifier: Programming Language :: Python :: 3.12
Classifier: Programming Language :: Python :: 3.13
Classifier: Programming Language :: Python :: Implementation :: CPython
Classifier: Programming Language :: Rust
Classifier: Topic :: Software Development :: Libraries :: Python Modules
Classifier: Topic :: Security
Classifier: Topic :: Text Processing :: Indexing
Classifier: Topic :: Scientific/Engineering :: Information Analysis
Classifier: Typing :: Typed
Summary: High-performance fuzzy hashing library implementing the DLAH (Dual-Layer Adaptive Hashing) algorithm. Powered by Rust for blazing fast performance.
Keywords: fuzzy-hashing,similarity,hash,fingerprint,dlah,duplicate-detection,text-similarity,file-similarity,content-hashing,malware-detection,plagiarism-detection
Author-email: LavinHash Contributors <contact@bdovenbird.com>
Maintainer-email: BDOvenbird Team <contact@bdovenbird.com>
License: MIT
Requires-Python: >=3.8
Project-URL: Homepage, https://bdovenbird.com/lavinhash/
Project-URL: Documentation, https://github.com/RafaCalRob/lavinhash#readme
Project-URL: Repository, https://github.com/RafaCalRob/lavinhash
Project-URL: Issues, https://github.com/RafaCalRob/lavinhash/issues
Project-URL: Changelog, https://github.com/RafaCalRob/lavinhash/blob/main/CHANGELOG.md
Project-URL: Demo, https://bdovenbird.com/lavinhash/demo
